housie/__init__.py
housie/__main__.py
housie/constants.py
housie/display_util.py
housie/game.py
housie/generate_ticket.py
housie/utils.py
housie/models/__init__.py
housie/models/board.py
housie/models/ticket.py
housie-0.2.1.dist-info/LICENSE.txt
housie-0.2.1.dist-info/METADATA
housie-0.2.1.dist-info/WHEEL
housie-0.2.1.dist-info/top_level.txt
housie-0.2.1.dist-info/RECORD
