Metadata-Version: 2.1
Name: housie
Version: 0.2.1
Summary: All the core logic for playing/simulating the popular game 'Housie' (also known as 'Bingo' or 'Tambola')
Author-email: Aaron Alphonso <alphonsoaaron19@gmail.com>
License: Apache License
Project-URL: source, https://github.com/aaronalphonso/housie
Keywords: python,housie,core,tambola,bingo,ticket,generator,board,game
Classifier: Programming Language :: Python :: 3
Classifier: License :: OSI Approved :: Apache Software License
Classifier: Operating System :: OS Independent
Requires-Python: >=3.6
License-File: LICENSE.txt
